eudi_wallet/__init__.py
eudi_wallet/did_jwt/__init__.py
eudi_wallet/did_jwt/signer_algorithm.py
eudi_wallet/did_jwt/util/__init__.py
eudi_wallet/did_jwt/util/json_canonicalize/Canonicalize.py
eudi_wallet/did_jwt/util/json_canonicalize/NumberToJson.py
eudi_wallet/did_jwt/util/json_canonicalize/__init__.py
eudi_wallet/did_key/__init__.py
eudi_wallet/ebsi_client/__init__.py
eudi_wallet/ebsi_did/__init__.py
eudi_wallet/ebsi_did_resolver/__init__.py
eudi_wallet/ebsi_did_resolver/constants/__init__.py
eudi_wallet/ebsi_did_resolver/validators/__init__.py
eudi_wallet/ethereum/__init__.py
eudi_wallet/ethereum/util.py
eudi_wallet/main.py
eudi_wallet/siop_auth/__init__.py
eudi_wallet/siop_auth/util.py
eudi_wallet/util/__init__.py
eudi_wallet/util/verifiable_presentation.py
eudi_wallet/validators/__init__.py
eudi_wallet/verifiable_credential/__init__.py
eudi_wallet/verifiable_credential/validators/__init__.py
eudi_wallet/verifiable_presentation/__init__.py
eudi_wallet/verifiable_presentation/v2/__init__.py
eudi_wallet-0.0.1.dist-info/LICENSE
eudi_wallet-0.0.1.dist-info/WHEEL
eudi_wallet-0.0.1.dist-info/METADATA
eudi_wallet-0.0.1.dist-info/RECORD
